{
  "project_info": {
    "project_number": "732138891007",
    "project_id": "thegabworkprojecttest",
    "storage_bucket": "thegabworkprojecttest.appspot.com"
  },
  "client": [
    {
      "client_info": {
        "mobilesdk_app_id": "1:732138891007:android:1e21290c90f733f4300eca",
        "android_client_info": {
          "package_name": "com.sardes.thegabworkproject"
        }
      },
      "oauth_client": [
        {
          "client_id": "732138891007-cd272etkj8s3vnggsgfuoanqkoeatkg1.apps.googleusercontent.com",
          "client_type": 3
        }
      ],
      "api_key": [
        {
          "current_key": "AIzaSyB3KFoWhuB8WCDE7SqAIr084gmM3hm9Oqc"
        }
      ],
      "services": {
        "appinvite_service": {
          "other_platform_oauth_client": [
            {
              "client_id": "732138891007-cd272etkj8s3vnggsgfuoanqkoeatkg1.apps.googleusercontent.com",
              "client_type": 3
            }
          ]
        }
      }
    }
  ],
  "configuration_version": "1"
}